pypointgroup/PointGroupApp.py
pypointgroup/PreBuild.py
pypointgroup/Version.py
pypointgroup/__init__.py
pypointgroup/core/Operators.py
pypointgroup/core/__init__.py
pypointgroup/core/__make_group_images.py
pypointgroup/core/_opers.py
pypointgroup/core/pgroupsgen.py
pypointgroup/core/symmetry.py
pypointgroup/gl/__init__.py
pypointgroup/gl/_gconsts.py
pypointgroup/gl/gbuilder.py
pypointgroup/gl/pgoprview.py
pypointgroup/gl/pgview.py
pypointgroup/gui/PGMainForm.py
pypointgroup/gui/__init__.py
pypointgroup/gui/pgContextMenu.py
pypointgroup/gui/tools.py
pypointgroup/gui/ui/__init__.py
pypointgroup/gui/ui/pgMainForm_ui.py
pypointgroup/img/2.BMP
pypointgroup/img/21SPh.bmp
pypointgroup/img/21SPv.bmp
pypointgroup/img/2SP.BMP
pypointgroup/img/3.BMP
pypointgroup/img/3I.BMP
pypointgroup/img/4.BMP
pypointgroup/img/41SP.BMP
pypointgroup/img/41iSP.bmp
pypointgroup/img/42SP.BMP
pypointgroup/img/42iSP.bmp
pypointgroup/img/4I.BMP
pypointgroup/img/6.BMP
pypointgroup/img/6I.BMP
pypointgroup/img/Icon.ico
pypointgroup/img/M.BMP
pypointgroup/img/Ma.bmp
pypointgroup/img/Mb.bmp
pypointgroup/img/Md.bmp
pypointgroup/img/pg_img_1.png
pypointgroup/img/pg_img_10.png
pypointgroup/img/pg_img_11.png
pypointgroup/img/pg_img_12.png
pypointgroup/img/pg_img_13.png
pypointgroup/img/pg_img_14.png
pypointgroup/img/pg_img_15.png
pypointgroup/img/pg_img_16.png
pypointgroup/img/pg_img_17.png
pypointgroup/img/pg_img_18.png
pypointgroup/img/pg_img_19.png
pypointgroup/img/pg_img_2.png
pypointgroup/img/pg_img_20.png
pypointgroup/img/pg_img_21.png
pypointgroup/img/pg_img_22.png
pypointgroup/img/pg_img_23.png
pypointgroup/img/pg_img_24.png
pypointgroup/img/pg_img_25.png
pypointgroup/img/pg_img_26.png
pypointgroup/img/pg_img_27.png
pypointgroup/img/pg_img_28.png
pypointgroup/img/pg_img_29.png
pypointgroup/img/pg_img_3.png
pypointgroup/img/pg_img_30.png
pypointgroup/img/pg_img_31.png
pypointgroup/img/pg_img_32.png
pypointgroup/img/pg_img_4.png
pypointgroup/img/pg_img_5.png
pypointgroup/img/pg_img_6.png
PyPointGroup-2.0.18.dist-info/METADATA
PyPointGroup-2.0.18.dist-info/WHEEL
PyPointGroup-2.0.18.dist-info/entry_points.txt
PyPointGroup-2.0.18.dist-info/top_level.txt
PyPointGroup-2.0.18.dist-info/RECORD
