Metadata-Version: 2.1
Name: PyPointGroup
Version: 2.0.18
Summary: Point group symmetry study software
Home-page: https://github.com/nik0380/pypointgroup
Author: Nikolay Somov
Author-email: somov@phys.unn.ru
License: MIT
Keywords: symmetry,group,crystallography,xray
Requires-Python: >3.4
Requires-Dist: PyQt5
Requires-Dist: numpy
Requires-Dist: PyOpenGL
Requires-Dist: pyshortcuts
